LICENSE.txt
setup.py
drav_id_TIK_afrit/__init__.py
drav_id_TIK_afrit/draver_id.py
tik_devices_afriton.egg-info/PKG-INFO
tik_devices_afriton.egg-info/SOURCES.txt
tik_devices_afriton.egg-info/dependency_links.txt
tik_devices_afriton.egg-info/top_level.txt